ktextaug/__init__.py
ktextaug/augmentation.py
ktextaug/file_utils.py
ktextaug/tokenization_utils.py
ktextaug/vocab_noised.txt
ktextaug/__pycache__/__init__.cpython-38.pyc
ktextaug/__pycache__/augmentation.cpython-38.pyc
ktextaug/__pycache__/file_utils.cpython-38.pyc
ktextaug/__pycache__/tokenization_utils.cpython-38.pyc
ktextaug/transformative/__init__.py
ktextaug/transformative/back_translation.py
ktextaug/transformative/noise_addition.py
ktextaug/transformative/random_process.py
ktextaug/transformative/stopwords-ko.txt
ktextaug/transformative/synonym_replacement.py
ktextaug/transformative/utils.py
ktextaug/transformative/__pycache__/__init__.cpython-38.pyc
ktextaug/transformative/__pycache__/back_translation.cpython-38.pyc
ktextaug/transformative/__pycache__/noise_addition.cpython-38.pyc
ktextaug/transformative/__pycache__/random_process.cpython-38.pyc
ktextaug/transformative/__pycache__/synonym_replacement.cpython-38.pyc
ktextaug/transformative/__pycache__/utils.cpython-38.pyc
ktextaug-0.1.9.dist-info/LICENSE
ktextaug-0.1.9.dist-info/METADATA
ktextaug-0.1.9.dist-info/WHEEL
ktextaug-0.1.9.dist-info/top_level.txt
ktextaug-0.1.9.dist-info/RECORD
