Metadata-Version: 2.1
Name: ktextaug
Version: 0.1.9
Summary: data augmentation tool for Korean
Home-page: https://github.com/jucho2725/ktextaug
Author: jinuk.cho, eddie.jeon, jonghyeok.park, junghoon.lee, minsu.jeong. all from ING Lab, SKKU.
Author-email: cju2725@gmail.com
License: UNKNOWN
Download-URL: https://github.com/jucho2725/ktextaug/archive/master.zip
Keywords: text augmentation,korean
Platform: UNKNOWN
Classifier: Programming Language :: Python :: 3
Classifier: Programming Language :: Python :: 3.2
Classifier: Programming Language :: Python :: 3.3
Classifier: Programming Language :: Python :: 3.4
Classifier: Programming Language :: Python :: 3.5
Classifier: Programming Language :: Python :: 3.6
Classifier: Programming Language :: Python :: 3.7
Classifier: Programming Language :: Python :: 3.8
Requires-Python: >=3.6
Requires-Dist: beautifulsoup4 (>=4.6.0)
Requires-Dist: googletrans (==3.1.0a0)
Requires-Dist: konlpy (>=0.5.2)
Requires-Dist: pykomoran (>=0.1.5)
Requires-Dist: transformers (>=2.6.0)
Provides-Extra: dev
Requires-Dist: pytest ; extra == 'dev'
Requires-Dist: flake8 ; extra == 'dev'
